[
    {
        "title": "疗伤烧肉粽",
        "artist": "周杰伦",
        "url": "music/疗伤烧肉粽.mp3"
    },
    {
        "title": "大笨钟",
        "artist": "周杰伦",
        "url": "music/大笨钟.mp3"
    },
    {
        "title": "安静",
        "artist": "周杰伦",
        "url": "music/安静.mp3"
    },
    {
        "title": "黑色毛衣",
        "artist": "周杰伦",
        "url": "music/黑色毛衣.mp3"
    },
    {
        "title": "开不了口",
        "artist": "周杰伦",
        "url": "music/开不了口.mp3"
    },
    {
        "title": "麦芽糖",
        "artist": "周杰伦",
        "url": "music/麦芽糖.mp3"
    },
    {
        "title": "傻笑",
        "artist": "周杰伦",
        "url": "music/傻笑.mp3"
    },
    {
        "title": "自导自演",
        "artist": "周杰伦",
        "url": "music/自导自演.mp3"
    },
    {
        "title": "手写的从前",
        "artist": "周杰伦",
        "url": "music/手写的从前.mp3"
    },
    {
        "title": "跨时代",
        "artist": "周杰伦",
        "url": "music/跨时代.mp3"
    },
    {
        "title": "听见下雨的声音",
        "artist": "周杰伦",
        "url": "music/听见下雨的声音.mp3"
    },
    {
        "title": "梦想启动",
        "artist": "周杰伦",
        "url": "music/梦想启动.mp3"
    },
    {
        "title": "世界末未日",
        "artist": "周杰伦",
        "url": "music/世界末未日.mp3"
    },
    {
        "title": "比较大的大提琴",
        "artist": "周杰伦",
        "url": "music/比较大的大提琴.mp3"
    },
    {
        "title": "我要夏天",
        "artist": "周杰伦",
        "url": "music/我要夏天.mp3"
    },
    {
        "title": "爱的飞行日记",
        "artist": "周杰伦",
        "url": "music/爱的飞行日记.mp3"
    },
    {
        "title": "飘移",
        "artist": "周杰伦",
        "url": "music/飘移.mp3"
    },
    {
        "title": "四季列车",
        "artist": "周杰伦",
        "url": "music/四季列车.mp3"
    },
    {
        "title": "逆鳞",
        "artist": "周杰伦",
        "url": "music/逆鳞.mp3"
    },
    {
        "title": "完美主义",
        "artist": "周杰伦",
        "url": "music/完美主义.mp3"
    },
    {
        "title": "心雨",
        "artist": "周杰伦",
        "url": "music/心雨.mp3"
    },
    {
        "title": "蛇舞",
        "artist": "周杰伦",
        "url": "music/蛇舞.mp3"
    },
    {
        "title": "说了再见",
        "artist": "周杰伦",
        "url": "music/说了再见.mp3"
    },
    {
        "title": "娘子",
        "artist": "周杰伦",
        "url": "music/娘子.mp3"
    },
    {
        "title": "本草纲目",
        "artist": "周杰伦",
        "url": "music/本草纲目.mp3"
    },
    {
        "title": "园游会",
        "artist": "周杰伦",
        "url": "music/园游会.mp3"
    },
    {
        "title": "烟花易冷",
        "artist": "周杰伦",
        "url": "music/烟花易冷.mp3"
    },
    {
        "title": "对不起",
        "artist": "周杰伦",
        "url": "music/对不起.mp3"
    },
    {
        "title": "免费教学录影带",
        "artist": "周杰伦",
        "url": "music/免费教学录影带.mp3"
    },
    {
        "title": "乱舞春秋",
        "artist": "周杰伦",
        "url": "music/乱舞春秋.mp3"
    },
    {
        "title": "阳明山",
        "artist": "周杰伦",
        "url": "music/阳明山.mp3"
    },
    {
        "title": "斗牛",
        "artist": "周杰伦",
        "url": "music/斗牛.mp3"
    },
    {
        "title": "她的睫毛",
        "artist": "周杰伦",
        "url": "music/她的睫毛.mp3"
    },
    {
        "title": "以父之名",
        "artist": "周杰伦",
        "url": "music/以父之名.mp3"
    },
    {
        "title": "爱你没差",
        "artist": "周杰伦",
        "url": "music/爱你没差.mp3"
    },
    {
        "title": "说好的幸福呢",
        "artist": "周杰伦",
        "url": "music/说好的幸福呢.mp3"
    },
    {
        "title": "彩虹",
        "artist": "周杰伦",
        "url": "music/彩虹.mp3"
    },
    {
        "title": "龙战骑士",
        "artist": "周杰伦",
        "url": "music/龙战骑士.mp3"
    },
    {
        "title": "印第安老斑鸠",
        "artist": "周杰伦",
        "url": "music/印第安老斑鸠.mp3"
    },
    {
        "title": "止战之殇",
        "artist": "周杰伦",
        "url": "music/止战之殇.mp3"
    },
    {
        "title": "半兽人",
        "artist": "周杰伦",
        "url": "music/半兽人.mp3"
    },
    {
        "title": "星晴",
        "artist": "周杰伦",
        "url": "music/星晴.mp3"
    },
    {
        "title": "威廉古堡",
        "artist": "周杰伦",
        "url": "music/威廉古堡.mp3"
    },
    {
        "title": "分裂",
        "artist": "周杰伦",
        "url": "music/分裂.mp3"
    },
    {
        "title": "一口气全念对",
        "artist": "周杰伦",
        "url": "music/一口气全念对.mp3"
    },
    {
        "title": "无双",
        "artist": "周杰伦",
        "url": "music/无双.mp3"
    },
    {
        "title": "搁浅",
        "artist": "周杰伦",
        "url": "music/搁浅.mp3"
    },
    {
        "title": "公主病",
        "artist": "周杰伦",
        "url": "music/公主病.mp3"
    },
    {
        "title": "嘻哈空姐",
        "artist": "周杰伦",
        "url": "music/嘻哈空姐.mp3"
    },
    {
        "title": "爱情废柴",
        "artist": "周杰伦",
        "url": "music/爱情废柴.mp3"
    }
]